{
	"uuid": "ae9ee197-dc0f-48a9-88b1-6025260f67b3",
	"version": "1488801522",
	"name": "percentile_approx(DOUBLE col, array(p1 [, p2]...) [, B])",
	"desc": "Same as above, but accepts and returns an array of percentile values instead of a single one",
	"createdBy": {
		"ref": {
			"type": "user",
			"uuid": "d04716df-e96a-419f-9118-c81342b47f85"
		}
	},
	"createdOn": "Mon, 06 Mar 2017 05:28:41 IST",
	"paramInfo" : [ 
       {
           "paramId" : "0",
           "paramName" : "col",
           "paramType" : "double",
           "paramReq" : "Y",
           "paramDefVal":""
       },
	   {
           "paramId" : "1",
           "paramName" : "p1",
           "paramType" : "array",
           "paramReq" : "N",
           "paramDefVal":""
       }
   ],
	"tags": [
		"DEV",
		"1.0.1",
		"DEMO"
	],
	"active": "Y",
        "published" : "N",
	"inputReq": "Y",
	"appInfo": [{
		"ref": {
			"type": "application",
			"uuid": "d7c11fd7-ec1a-40c7-ba25-7da1e8b730cb",
			"version": "1464977196"
		}
	}],
	"functionInfo": "percentile_approx",
	"funcType": "hive",
	"category": "aggregate"
}
