{
	"uuid" : "9d366adc-4925-11e8-842f-0ed5f89f718b",
	"name" : "OperatorDelete",
	"version" : "1464977196",
	"desc" : "Privilage for Delete",
	"createdBy" : {
		"ref" : {
			"type" : "user",
			"uuid" : "d04716df-e96a-419f-9118-c81342b47f85"
		}
	},
	"createdOn" : ISODate("2019-04-16T14:28:17.683Z"),
	"active" : "Y",
	"locked" : "N",
	"privType" : "Delete",
	"metaId" : {
		"ref" : {
			"type" : "meta",
			"uuid" : "0500c69c-4937-11e8-842f-0ed5f89f718b"
		}
	},
	"appInfo" : [
		{
			"ref" : {
				"type" : "application",
				"uuid" : "d7c11fd7-ec1a-40c7-ba25-7da1e8b730cb"
			}
		}
	],
	"publicFlag" : "Y",
	"displayName" : "OperatorDelete"
}
