{
	"uuid" : "aae63a56-cf40-43a0-b0fc-3d1110742a98",
	"name" : "TagExport",
	"version" : "1464977196",
	"desc" : "Privilage for Export",
	"createdBy" : {
		"ref" : {
			"type" : "user",
			"uuid" : "d04716df-e96a-419f-9118-c81342b47f85"
		}
	},
	"createdOn" : ISODate("2019-03-18T14:21:59.582Z"),
	"active" : "Y",
	"locked" : "N",
	"privType" : "Export",
	"metaId" : {
		"ref" : {
			"type" : "meta",
			"uuid" : "181e5151-1510-42be-acf3-bc0309257851"
		}
	},
	"appInfo" : [
		{
			"ref" : {
				"type" : "application",
				"uuid" : "d7c11fd7-ec1a-40c7-ba25-7da1e8b730cb"
			}
		}
	],
	"publicFlag" : "Y"
}
