{
  "id": "5aedc111b1dfe37d8ec87bf7",
  "uuid": "1f21db3e-7009-45af-bca0-5559f8b29e21",
  "version": "1525530897",
  "name": "paramlist_transpose",
  "desc": null,
  "createdBy": {
    "ref": {
      "type": "user",
      "uuid": "d04716df-e96a-419f-9118-c81342b47f86",
      "version": "1464977196"
      
    },
    "value": null
  },
	"createdOn": ISODate("2017-11-07T10:24:13.443Z"),
  "tags": [],
  "active": "Y",
  "published": "N",
  "appInfo": [
    {
      "ref": {
        "type": "application",
        "uuid": "d7c11fd7-ec1a-40c7-ba25-7da1e8b730cd",
        "version": "1464977196"
       
      },
      "value": null
    }
  ],
  "params": [
    {
      "paramId": "0",
      "paramName": "sourceDatapod",
      "paramType": "attributes",
      "paramValue": null,
      "paramRef": null
    },
    {
      "paramId": "1",
      "paramName": "key",
      "paramType": "attribute",
      "paramValue": null,
      "paramRef": null
    },
    {
      "paramId": "2",
      "paramName": "saveLocation",
      "paramType": "attribute",
      "paramValue": null,
      "paramRef": null
    }
  ]
}
